{"Reservoir Computing": {"2508.02407": "|**2025-08-04**|**Quantum Machine Learning-based Test Oracle for Autonomous Mobile Robots**|Xinyi Wang et.al.|[2508.02407](http://arxiv.org/abs/2508.02407)|null|\n", "2508.02218": "|**2025-08-04**|**Reservoir Computing with Evolved Critical Neural Cellular Automata**|Sidney Pontes-Filho et.al.|[2508.02218](http://arxiv.org/abs/2508.02218)|null|\n", "2507.23689": "|**2025-08-01**|**Probing graph topology from local quantum measurements**|F. Romeo et.al.|[2507.23689](http://arxiv.org/abs/2507.23689)|null|\n", "2507.21496": "|**2025-07-29**|**Multifunctional physical reservoir computing in soft tensegrity robots**|Ryo Terajima et.al.|[2507.21496](http://arxiv.org/abs/2507.21496)|null|\n", "2507.21377": "|**2025-07-28**|**Reservoir Computation with Networks of Differentiating Neuron Ring Oscillators**|Alexander Yeung et.al.|[2507.21377](http://arxiv.org/abs/2507.21377)|null|\n", "2507.19046": "|**2025-07-25**|**Dynamics-Informed Reservoir Computing with Visibility Graphs**|Charlotte Geier et.al.|[2507.19046](http://arxiv.org/abs/2507.19046)|null|\n", "2507.18423": "|**2025-07-24**|**Multi-Model Ensemble and Reservoir Computing for River Discharge Prediction in Ungauged Basins**|Mizuki Funato et.al.|[2507.18423](http://arxiv.org/abs/2507.18423)|null|\n", "2507.17115": "|**2025-07-23**|**Stochastically Structured Reservoir Computers for Financial and Economic System Identification**|Lendy Banegas et.al.|[2507.17115](http://arxiv.org/abs/2507.17115)|null|\n", "2507.15779": "|**2025-07-30**|**Reservoir Computing as a Language Model**|Felix K\u00f6ster et.al.|[2507.15779](http://arxiv.org/abs/2507.15779)|null|\n", "2507.15158": "|**2025-07-25**|**Resonant-Tunnelling Diode Reservoir Computing System for Image Recognition**|A. H. Abbas et.al.|[2507.15158](http://arxiv.org/abs/2507.15158)|null|\n"}, "ESN": {"2507.18467": "|**2025-07-24**|**Contraction, Criticality, and Capacity: A Dynamical-Systems Perspective on Echo-State Networks**|Pradeep Singh et.al.|[2507.18467](http://arxiv.org/abs/2507.18467)|null|\n", "2507.06050": "|**2025-07-08**|**Minimal Deterministic Echo State Networks Outperform Random Reservoirs in Learning Chaotic Dynamics**|Francesco Martinuzzi et.al.|[2507.06050](http://arxiv.org/abs/2507.06050)|null|\n", "2506.21918": "|**2025-07-17**|**Model-free Forecasting of Rogue Waves using Reservoir Computing**|Abrari Noor Hasmi et.al.|[2506.21918](http://arxiv.org/abs/2506.21918)|null|\n", "2507.02917": "|**2025-06-25**|**Echo State Transformer: When chaos brings memory**|Yannis Bendi-Ouis et.al.|[2507.02917](http://arxiv.org/abs/2507.02917)|null|\n", "2506.01755": "|**2025-06-03**|**Data-assimilated model-informed reinforcement learning**|Defne E. Ozan et.al.|[2506.01755](http://arxiv.org/abs/2506.01755)|null|\n", "2505.24099": "|**2025-05-30**|**Attractor learning for spatiotemporally chaotic dynamical systems using echo state networks with transfer learning**|Mohammad Shah Alam et.al.|[2505.24099](http://arxiv.org/abs/2505.24099)|null|\n", "2505.22985": "|**2025-05-29**|**Knowledge Distillation for Reservoir-based Classifier: Human Activity Recognition**|Masaharu Kagiyama et.al.|[2505.22985](http://arxiv.org/abs/2505.22985)|null|\n", "2505.22837": "|**2025-05-28**|**Quantum Reservoir Computing for Corrosion Prediction in Aerospace: A Hybrid Approach for Enhanced Material Degradation Forecasting**|Akshat Tandon et.al.|[2505.22837](http://arxiv.org/abs/2505.22837)|null|\n", "2505.17740": "|**2025-05-23**|**A tensor network approach for chaotic time series prediction**|Rodrigo Mart\u00ednez-Pe\u00f1a et.al.|[2505.17740](http://arxiv.org/abs/2505.17740)|null|\n", "2505.16208": "|**2025-05-22**|**Using Echo-State Networks to Reproduce Rare Events in Chaotic Systems**|Anton Erofeev et.al.|[2505.16208](http://arxiv.org/abs/2505.16208)|null|\n"}, "LSM": {"2504.09796": "|**2025-04-14**|**Advancing RFI-Detection in Radio Astronomy with Liquid State Machines**|Nicholas J Pritchard et.al.|[2504.09796](http://arxiv.org/abs/2504.09796)|null|\n", "2503.06798": "|**2025-03-09**|**Characterizing Learning in Spiking Neural Networks with Astrocyte-Like Units**|Christopher S. Yang et.al.|[2503.06798](http://arxiv.org/abs/2503.06798)|null|\n", "2411.19209": "|**2025-01-29**|**A spiking photonic neural network of 40.000 neurons, trained with rank-order coding for leveraging sparsity**|Ria Talukder et.al.|[2411.19209](http://arxiv.org/abs/2411.19209)|null|\n", "2411.11414": "|**2024-11-18**|**Temporal and Spatial Reservoir Ensembling Techniques for Liquid State Machines**|Anmol Biswas et.al.|[2411.11414](http://arxiv.org/abs/2411.11414)|null|\n", "2407.20590": "|**2024-07-30**|**Exploring Liquid Neural Networks on Loihi-2**|Wiktoria Agata Pawlak et.al.|[2407.20590](http://arxiv.org/abs/2407.20590)|null|\n", "2307.00771": "|**2025-01-10**|**Resistive memory-based zero-shot liquid state machine for multimodal event data learning**|Ning Lin et.al.|[2307.00771](http://arxiv.org/abs/2307.00771)|null|\n", "2306.11640": "|**2023-06-20**|**Process Voltage Temperature Variability Estimation of Tunneling Current for Band-to-Band-Tunneling based Neuron**|Shubham Patil et.al.|[2306.11640](http://arxiv.org/abs/2306.11640)|null|\n", "2304.01015": "|**2023-03-31**|**Adaptive structure evolution and biologically plausible synaptic plasticity for recurrent spiking neural networks**|Wenxuan Pan et.al.|[2304.01015](http://arxiv.org/abs/2304.01015)|null|\n", "2302.03506": "|**2023-09-10**|**Dynamic Training of Liquid State Machines**|Pavithra Koralalage et.al.|[2302.03506](http://arxiv.org/abs/2302.03506)|null|\n", "2212.12908": "|**2022-12-25**|**Sitting Posture Recognition Using a Spiking Neural Network**|Jianquan Wang et.al.|[2212.12908](http://arxiv.org/abs/2212.12908)|null|\n"}}